vibelinter/data/.gitignore
vibelinter/__init__.py
vibelinter/__main__.py
vibelinter/cli.py
vibelinter/configuration.py
vibelinter/engine.py
vibelinter/exceptions.py
vibelinter/py.typed
vibelinter/__/__init__.py
vibelinter/__/imports.py
vibelinter/__/nomina.py
vibelinter/rules/__.py
vibelinter/rules/__init__.py
vibelinter/rules/base.py
vibelinter/rules/context.py
vibelinter/rules/registry.py
vibelinter/rules/violations.py
vibelinter/rules/implementations/__.py
vibelinter/rules/implementations/__init__.py
vibelinter/rules/implementations/vbl101.py
vibelinter/rules/implementations/vbl201.py
vibelinter/rules/implementations/vbl202.py
emcd_vibe_linter-1.0a2.dist-info/METADATA
emcd_vibe_linter-1.0a2.dist-info/WHEEL
emcd_vibe_linter-1.0a2.dist-info/entry_points.txt
emcd_vibe_linter-1.0a2.dist-info/licenses/LICENSE.txt
emcd_vibe_linter-1.0a2.dist-info/RECORD
