Metadata-Version: 2.4
Name: emcd-vibe-linter
Version: 1.0a2
Summary: LibCST-based Python linter. (Vibe-coded.)
Project-URL: Homepage, https://github.com/emcd/vibe-py-linter
Project-URL: Documentation, https://emcd.github.io/vibe-py-linter
Project-URL: Download, https://pypi.org/project/emcd-vibe-linter/#files
Project-URL: Source Code, https://github.com/emcd/vibe-py-linter
Project-URL: Issue Tracker, https://github.com/emcd/vibe-py-linter/issues
Author-email: Eric McDonald <emcd@users.noreply.github.com>
License-Expression: Apache-2.0
License-File: LICENSE.txt
Keywords: lint,linter
Classifier: Development Status :: 3 - Alpha
Classifier: Intended Audience :: Developers
Classifier: License :: OSI Approved :: Apache Software License
Classifier: Programming Language :: Python :: 3 :: Only
Classifier: Programming Language :: Python :: 3.10
Classifier: Programming Language :: Python :: 3.11
Classifier: Programming Language :: Python :: 3.12
Classifier: Programming Language :: Python :: 3.13
Classifier: Programming Language :: Python :: 3.14
Classifier: Programming Language :: Python :: Implementation :: CPython
Classifier: Programming Language :: Python :: Implementation :: PyPy
Classifier: Topic :: Software Development
Requires-Python: >=3.10
Requires-Dist: absence~=1.1
Requires-Dist: accretive~=4.2
Requires-Dist: dynadoc~=1.4
Requires-Dist: emcd-appcore[cli]~=1.6
Requires-Dist: frigid~=4.2
Requires-Dist: libcst
Requires-Dist: tomli
Requires-Dist: typing-extensions
Requires-Dist: wcmatch
